doggomenus/__init__.py
doggomenus/command.py
doggomenus/errors.py
doggomenus/selection.py
DoggoMenus-1.0.3.dist-info/LICENSE
DoggoMenus-1.0.3.dist-info/METADATA
DoggoMenus-1.0.3.dist-info/WHEEL
DoggoMenus-1.0.3.dist-info/top_level.txt
DoggoMenus-1.0.3.dist-info/RECORD
