Metadata-Version: 2.1
Name: DoggoMenus
Version: 1.0.3
Summary: A basic console menu system for Python!
Home-page: https://github.com/Taromaruu/DoggoMenus
Author: Doggotaco
Author-email: taromaruyuki@gmail.com
License: UNKNOWN
Platform: UNKNOWN
Classifier: Programming Language :: Python :: 3
Classifier: License :: OSI Approved :: MIT License
Classifier: Operating System :: OS Independent
Requires-Python: >=3.6
Requires-Dist: py-getch
